setup.py
couchdb_auditor/__init__.py
couchdb_auditor/auditor.py
couchdb_auditor.egg-info/PKG-INFO
couchdb_auditor.egg-info/SOURCES.txt
couchdb_auditor.egg-info/dependency_links.txt
couchdb_auditor.egg-info/entry_points.txt
couchdb_auditor.egg-info/requires.txt
couchdb_auditor.egg-info/top_level.txt