Metadata-Version: 1.0
Name: couchdb-auditor
Version: 0.2
Summary: Audit configuration and security issues for an Apache CouchDB server.
Home-page: http://code.google.com/p/couchdb-auditor/
Author: Alexander Shorin
Author-email: kxepal@gmail.com
License: BSD
Platform: UNKNOWN
